<?xml version="1.0" encoding="utf-8"?>
<Projectiles>
    <Bile>
        <EntityTag>Bile</EntityTag>
        <Speed>320</Speed>
		<TimeToLive>7</TimeToLive>
		<FadeSpeed>3.0</FadeSpeed>
		<Damage>30</Damage>

		<GroundOffset>
            <Level1>55</Level1>
			<Level2>40</Level2>
            <Level3>40</Level3> <!-- CHECK THIS VALUE -->
            <Level4>40</Level4> <!-- CHECK THIS VALUE -->
		</GroundOffset>
		
		<!-- The smaller the value, the further it will go. 
		     Think of the a in a quadratic function (y = ax^2 + b).
             Will have to increase speed as Distance gets smaller. -->
		<Distance>0.06</Distance>
    </Bile>
    <Bullet>
        <EntityTag>Bullet</EntityTag>
		<Speed>400</Speed>
		<RotationSpeed>1000</RotationSpeed>
		<FadeSpeed>1.3</FadeSpeed>
		<Damage>30</Damage>
	</Bullet>
</Projectiles>
